igraphGraspi/__init__.py
igraphGraspi/csvFileMaker.py
igraphGraspi/igraph_testing.py
igraphGraspi/testFileMaker.py
igraphGraspi-1.0.0.dist-info/METADATA
igraphGraspi-1.0.0.dist-info/WHEEL
igraphGraspi-1.0.0.dist-info/top_level.txt
igraphGraspi-1.0.0.dist-info/RECORD
