Metadata-Version: 2.1
Name: igraphGraspi
Version: 1.0.0
Summary: Graspi igraph
Home-page: https://github.com/kkevinmartinezz/igraphGraspi.git
Author: Kevin Martinez
Author-email: kem44@buffalo.edu
License: Apache License 2.0
Requires-Dist: igraph
Requires-Dist: contourpy
Requires-Dist: cycler
Requires-Dist: fonttools
Requires-Dist: kiwisolver
Requires-Dist: matplotlib
Requires-Dist: numpy
Requires-Dist: packaging
Requires-Dist: pillow
Requires-Dist: psutil
Requires-Dist: pyparsing
Requires-Dist: python-dateutil
Requires-Dist: six
Requires-Dist: texttable
